{
  "name": "Unsafe Dark",
  "type": "dark",
  "colors": {
    "editor.background": "#111111",
    "editor.foreground": "#E8E9EB",
    "editorLineNumber.foreground": "#333333",
    "editorLineNumber.activeForeground": "#666666",

    "activityBar.background": "#111111",
    "activityBar.foreground": "#888888",
    "activityBar.inactiveForeground": "#333333",
    "activityBar.border": "#242424",
    "activityBarBadge.background": "#0075DE",
    "activityBarBadge.foreground": "#FFFFFF",

    "sideBar.background": "#111111",
    "sideBar.foreground": "#C0C0C0",
    "sideBar.border": "#242424",
    "sideBar.emptyBackground": "#111111",
    "sideBarTitle.foreground": "#555555",
    "sideBarSectionHeader.background": "#111111",
    "sideBarSectionHeader.foreground": "#555555",
    "sideBarSectionHeader.border": "#242424",

    "statusBar.background": "#111111",
    "statusBar.foreground": "#555555",
    "statusBar.border": "#242424",
    "statusBar.debuggingBackground": "#0075DE",
    "statusBar.debuggingForeground": "#FFFFFF",
    "statusBar.noFolderBackground": "#111111",

    "titleBar.activeBackground": "#111111",
    "titleBar.activeForeground": "#C0C0C0",
    "titleBar.inactiveBackground": "#111111",
    "titleBar.inactiveForeground": "#333333",
    "titleBar.border": "#242424",

    "panel.background": "#111111",
    "panel.border": "#242424",
    "panelTitle.activeForeground": "#E8E9EB",
    "panelTitle.activeBorder": "#0075DE",
    "panelTitle.inactiveForeground": "#333333",

    "editorGroupHeader.tabsBackground": "#111111",
    "editorGroupHeader.tabsBorder": "#242424",
    "tab.activeBackground": "#111111",
    "tab.activeForeground": "#E8E9EB",
    "tab.activeBorder": "#0075DE",
    "tab.inactiveBackground": "#111111",
    "tab.inactiveForeground": "#333333",
    "tab.border": "#242424",
    "tab.hoverBackground": "#191919",
    "tab.unfocusedActiveBackground": "#111111",
    "tab.unfocusedActiveForeground": "#666666",

    "terminal.background": "#111111",
    "terminal.foreground": "#C0C0C0",
    "terminal.border": "#242424",

    "editor.lineHighlightBackground": "#181818",
    "editor.lineHighlightBorder": "#1E1E1E",
    "editor.selectionBackground": "#0075DE33",
    "editor.selectionHighlightBackground": "#0075DE18",
    "editor.inactiveSelectionBackground": "#0075DE1A",
    "editor.findMatchBackground": "#D4890040",
    "editor.findMatchHighlightBackground": "#D4890022",
    "editorCursor.foreground": "#E8E9EB",
    "editorCursor.background": "#111111",
    "editorWhitespace.foreground": "#222222",
    "editorBracketMatch.background": "#191919",
    "editorBracketMatch.border": "#242424",
    "editorIndentGuide.background1": "#1E1E1E",
    "editorIndentGuide.activeBackground1": "#2E2E2E",
    "editorRuler.foreground": "#242424",
    "editorOverviewRuler.border": "#242424",

    "menu.background": "#191919",
    "menu.foreground": "#C0C0C0",
    "menu.selectionBackground": "#0075DE",
    "menu.selectionForeground": "#FFFFFF",
    "menu.separatorBackground": "#242424",
    "menu.border": "#242424",

    "button.background": "#0075DE",
    "button.hoverBackground": "#005BB5",
    "button.foreground": "#FFFFFF",
    "button.secondaryBackground": "#191919",
    "button.secondaryForeground": "#C0C0C0",
    "button.secondaryHoverBackground": "#222222",

    "input.background": "#191919",
    "input.border": "#242424",
    "input.foreground": "#E8E9EB",
    "input.placeholderForeground": "#333333",
    "inputOption.activeBorder": "#0075DE",
    "inputOption.activeBackground": "#0075DE22",

    "dropdown.background": "#191919",
    "dropdown.border": "#242424",
    "dropdown.foreground": "#C0C0C0",

    "list.activeSelectionBackground": "#191919",
    "list.activeSelectionForeground": "#E8E9EB",
    "list.hoverBackground": "#191919",
    "list.hoverForeground": "#C0C0C0",
    "list.inactiveSelectionBackground": "#111111",
    "list.inactiveSelectionForeground": "#888888",
    "list.focusBackground": "#191919",
    "list.focusForeground": "#E8E9EB",
    "list.highlightForeground": "#0075DE",

    "badge.background": "#0075DE",
    "badge.foreground": "#FFFFFF",
    "progressBar.background": "#0075DE",

    "scrollbar.shadow": "#00000055",
    "scrollbarSlider.background": "#242424",
    "scrollbarSlider.hoverBackground": "#2E2E2E",
    "scrollbarSlider.activeBackground": "#383838",

    "errorForeground": "#FF375F",
    "foreground": "#C0C0C0",
    "descriptionForeground": "#555555",
    "disabledForeground": "#333333",
    "focusBorder": "#0075DE",
    "selection.background": "#0075DE33",

    "editorWidget.background": "#191919",
    "editorWidget.border": "#242424",
    "editorSuggestWidget.background": "#191919",
    "editorSuggestWidget.border": "#242424",
    "editorSuggestWidget.foreground": "#C0C0C0",
    "editorSuggestWidget.selectedBackground": "#222222",
    "editorSuggestWidget.highlightForeground": "#0075DE",
    "editorHoverWidget.background": "#191919",
    "editorHoverWidget.border": "#242424",

    "notificationCenterHeader.background": "#191919",
    "notifications.background": "#191919",
    "notifications.border": "#242424",
    "notificationLink.foreground": "#0075DE",

    "quickInput.background": "#191919",
    "quickInput.foreground": "#C0C0C0",
    "quickInputTitle.background": "#111111",
    "quickInputList.focusBackground": "#222222",

    "peekView.border": "#242424",
    "peekViewEditor.background": "#111111",
    "peekViewEditor.matchHighlightBackground": "#D4890030",
    "peekViewResult.background": "#191919",
    "peekViewResult.matchHighlightBackground": "#D4890025",
    "peekViewResult.selectionBackground": "#222222",
    "peekViewTitle.background": "#191919",
    "peekViewTitleDescription.foreground": "#555555",
    "peekViewTitleLabel.foreground": "#E8E9EB",

    "diffEditor.insertedTextBackground": "#30D15818",
    "diffEditor.removedTextBackground": "#FF375F18",
    "diffEditor.insertedLineBackground": "#30D15810",
    "diffEditor.removedLineBackground": "#FF375F10",

    "gitDecoration.modifiedResourceForeground": "#D4A520",
    "gitDecoration.deletedResourceForeground": "#FF375F",
    "gitDecoration.untrackedResourceForeground": "#30D158",
    "gitDecoration.ignoredResourceForeground": "#333333",
    "gitDecoration.conflictingResourceForeground": "#FF9F0A",

    "breadcrumb.background": "#111111",
    "breadcrumb.foreground": "#333333",
    "breadcrumb.focusForeground": "#C0C0C0",
    "breadcrumb.activeSelectionForeground": "#E8E9EB",
    "breadcrumbPicker.background": "#191919",

    "settings.headerForeground": "#E8E9EB",
    "settings.modifiedItemIndicator": "#0075DE",
    "settings.dropdownBackground": "#191919",
    "settings.dropdownBorder": "#242424",
    "settings.checkboxBackground": "#191919",
    "settings.checkboxBorder": "#242424",
    "settings.textInputBackground": "#191919",
    "settings.textInputBorder": "#242424",
    "settings.numberInputBackground": "#191919",
    "settings.numberInputBorder": "#242424",

    "terminal.ansiBlack": "#111111",
    "terminal.ansiBlue": "#0075DE",
    "terminal.ansiGreen": "#30D158",
    "terminal.ansiYellow": "#D4A520",
    "terminal.ansiRed": "#FF375F",
    "terminal.ansiWhite": "#C0C0C0",
    "terminal.ansiCyan": "#32ADE6",
    "terminal.ansiMagenta": "#FF6B35",
    "terminal.ansiBrightBlack": "#444444",
    "terminal.ansiBrightBlue": "#3399FF",
    "terminal.ansiBrightGreen": "#30D158",
    "terminal.ansiBrightYellow": "#FFD60A",
    "terminal.ansiBrightRed": "#FF6B81",
    "terminal.ansiBrightWhite": "#E8E9EB",
    "terminal.ansiBrightCyan": "#64D2FF",
    "terminal.ansiBrightMagenta": "#FF9F0A",

    "contrastBorder": "#242424",
    "widget.shadow": "#00000077",
    "window.activeBorder": "#242424",
    "window.inactiveBorder": "#242424"
  },
  "tokenColors": [
    {
      "name": "Comment",
      "scope": ["comment", "punctuation.definition.comment"],
      "settings": { "foreground": "#3A3A3A", "fontStyle": "italic" }
    },
    {
      "name": "Invalid",
      "scope": ["invalid", "invalid.illegal"],
      "settings": { "foreground": "#FF375F" }
    },
    {
      "name": "Keyword, Storage, Control Flow",
      "scope": [
        "keyword", "storage.type", "storage.modifier",
        "keyword.control", "keyword.control.flow",
        "keyword.other.template", "keyword.other.substitution"
      ],
      "settings": { "foreground": "#FF6B6B" }
    },
    {
      "name": "Operator",
      "scope": [
        "keyword.operator", "keyword.operator.arithmetic",
        "keyword.operator.comparison", "keyword.operator.logical",
        "keyword.operator.assignment", "keyword.operator.new",
        "keyword.operator.delete"
      ],
      "settings": { "foreground": "#555555" }
    },
    {
      "name": "Punctuation",
      "scope": [
        "punctuation", "meta.tag", "punctuation.definition.tag",
        "punctuation.separator.inheritance.php",
        "punctuation.definition.tag.html",
        "punctuation.definition.tag.begin.html",
        "punctuation.definition.tag.end.html",
        "punctuation.section.embedded"
      ],
      "settings": { "foreground": "#4A4A4A" }
    },
    {
      "name": "Function, Method",
      "scope": [
        "entity.name.function", "meta.function-call", "variable.function",
        "support.function", "keyword.other.special-method",
        "entity.name.method.js",
        "meta.class-method.js entity.name.function.js",
        "variable.function.constructor"
      ],
      "settings": { "foreground": "#64B5F6" }
    },
    {
      "name": "String",
      "scope": [
        "string", "constant.other.symbol", "constant.other.key",
        "markup.inserted.git_gutter",
        "meta.group.braces.curly constant.other.object.key.js string.unquoted.label.js",
        "string.other.link"
      ],
      "settings": { "foreground": "#CE8C6A" }
    },
    {
      "name": "Number",
      "scope": [
        "constant.numeric", "support.constant", "constant.character",
        "constant.escape", "keyword.other.unit"
      ],
      "settings": { "foreground": "#D4A520" }
    },
    {
      "name": "Boolean, Null, Undefined",
      "scope": ["constant.language"],
      "settings": { "foreground": "#FF9F0A" }
    },
    {
      "name": "Class, Type, Support",
      "scope": [
        "entity.name", "support.class", "support.type",
        "support.other.namespace.use.php", "meta.use.php",
        "support.other.namespace.php", "support.type.sys-types",
        "entity.name.type", "entity.name.class", "markup.changed.git_gutter"
      ],
      "settings": { "foreground": "#E8A857" }
    },
    {
      "name": "Variable",
      "scope": [
        "variable", "string constant.other.placeholder",
        "meta.block variable.other", "support.other.variable",
        "entity.name.module.js", "variable.import.parameter.js",
        "variable.other.class.js"
      ],
      "settings": { "foreground": "#C0C0C0" }
    },
    {
      "name": "Function Parameter",
      "scope": ["variable.parameter"],
      "settings": { "foreground": "#A8A8A8" }
    },
    {
      "name": "This, Self",
      "scope": ["variable.language"],
      "settings": { "foreground": "#FF6B6B" }
    },
    {
      "name": "Tag",
      "scope": ["entity.name.tag", "meta.tag.sgml", "markup.deleted.git_gutter"],
      "settings": { "foreground": "#FF6B6B" }
    },
    {
      "name": "HTML / JSX Attribute",
      "scope": [
        "entity.other.attribute-name",
        "text.html.basic entity.other.attribute-name.html",
        "text.html.basic entity.other.attribute-name"
      ],
      "settings": { "foreground": "#D4A520" }
    },
    {
      "name": "CSS Property",
      "scope": [
        "source.css support.type.property-name",
        "source.sass support.type.property-name",
        "source.scss support.type.property-name",
        "source.less support.type.property-name",
        "source.stylus support.type.property-name",
        "source.postcss support.type.property-name"
      ],
      "settings": { "foreground": "#E8A857" }
    },
    {
      "name": "CSS Class",
      "scope": ["entity.other.attribute-name.class"],
      "settings": { "foreground": "#D4A520" }
    },
    {
      "name": "CSS ID",
      "scope": ["source.sass keyword.control"],
      "settings": { "foreground": "#FF6B6B" }
    },
    {
      "name": "Inserted",
      "scope": ["markup.inserted"],
      "settings": { "foreground": "#30D158" }
    },
    {
      "name": "Deleted",
      "scope": ["markup.deleted"],
      "settings": { "foreground": "#FF375F" }
    },
    {
      "name": "Changed",
      "scope": ["markup.changed"],
      "settings": { "foreground": "#D4A520" }
    },
    {
      "name": "Markup Heading, Inherited Class",
      "scope": ["entity.other.inherited-class", "markup.heading"],
      "settings": { "foreground": "#64B5F6" }
    },
    {
      "name": "Colors",
      "scope": ["constant.other.color"],
      "settings": { "foreground": "#E8E9EB" }
    },
    {
      "name": "Regular Expressions",
      "scope": ["string.regexp"],
      "settings": { "foreground": "#FF9F0A" }
    },
    {
      "name": "Escape Characters",
      "scope": ["constant.character.escape"],
      "settings": { "foreground": "#FF9F0A" }
    },
    {
      "name": "URL",
      "scope": ["*url*", "*link*", "*uri*"],
      "settings": { "fontStyle": "underline" }
    },
    {
      "name": "Decorators",
      "scope": [
        "tag.decorator.js entity.name.tag.js",
        "tag.decorator.js punctuation.definition.tag.js"
      ],
      "settings": { "foreground": "#FF6B6B" }
    },
    {
      "name": "ES7 Bind Operator",
      "scope": ["source.js constant.other.object.key.js string.unquoted.label.js"],
      "settings": { "foreground": "#555555" }
    },
    {
      "name": "JSON Key - Level 0",
      "scope": ["source.json meta.structure.dictionary.json support.type.property-name.json"],
      "settings": { "foreground": "#FF6B6B" }
    },
    {
      "name": "JSON Key - Level 1",
      "scope": ["source.json meta.structure.dictionary.json meta.structure.dictionary.value.json meta.structure.dictionary.json support.type.property-name.json"],
      "settings": { "foreground": "#64B5F6" }
    },
    {
      "name": "JSON Key - Level 2",
      "scope": ["source.json meta.structure.dictionary.json meta.structure.dictionary.value.json meta.structure.dictionary.json meta.structure.dictionary.value.json meta.structure.dictionary.json support.type.property-name.json"],
      "settings": { "foreground": "#E8A857" }
    },
    {
      "name": "JSON Key - Level 3",
      "scope": ["source.json meta.structure.dictionary.json meta.structure.dictionary.value.json meta.structure.dictionary.json meta.structure.dictionary.value.json meta.structure.dictionary.json meta.structure.dictionary.value.json meta.structure.dictionary.json support.type.property-name.json"],
      "settings": { "foreground": "#D4A520" }
    },
    {
      "name": "JSON Key - Level 4",
      "scope": ["source.json meta.structure.dictionary.json meta.structure.dictionary.value.json meta.structure.dictionary.json meta.structure.dictionary.value.json meta.structure.dictionary.json meta.structure.dictionary.value.json meta.structure.dictionary.json meta.structure.dictionary.value.json meta.structure.dictionary.json support.type.property-name.json"],
      "settings": { "foreground": "#CE8C6A" }
    },
    {
      "name": "JSON Key - Level 5",
      "scope": ["source.json meta.structure.dictionary.json meta.structure.dictionary.value.json meta.structure.dictionary.json meta.structure.dictionary.value.json meta.structure.dictionary.json meta.structure.dictionary.value.json meta.structure.dictionary.json meta.structure.dictionary.value.json meta.structure.dictionary.json meta.structure.dictionary.value.json meta.structure.dictionary.json support.type.property-name.json"],
      "settings": { "foreground": "#FF6B6B" }
    },
    {
      "name": "JSON Key - Level 6",
      "scope": ["source.json meta.structure.dictionary.json meta.structure.dictionary.value.json meta.structure.dictionary.json meta.structure.dictionary.value.json meta.structure.dictionary.json meta.structure.dictionary.value.json meta.structure.dictionary.json meta.structure.dictionary.value.json meta.structure.dictionary.json meta.structure.dictionary.value.json meta.structure.dictionary.json meta.structure.dictionary.value.json meta.structure.dictionary.json support.type.property-name.json"],
      "settings": { "foreground": "#64B5F6" }
    },
    {
      "name": "JSON Key - Level 7",
      "scope": ["source.json meta.structure.dictionary.json meta.structure.dictionary.value.json meta.structure.dictionary.json meta.structure.dictionary.value.json meta.structure.dictionary.json meta.structure.dictionary.value.json meta.structure.dictionary.json meta.structure.dictionary.value.json meta.structure.dictionary.json meta.structure.dictionary.value.json meta.structure.dictionary.json meta.structure.dictionary.value.json meta.structure.dictionary.json meta.structure.dictionary.value.json meta.structure.dictionary.json support.type.property-name.json"],
      "settings": { "foreground": "#E8A857" }
    },
    {
      "name": "JSON Key - Level 8",
      "scope": ["source.json meta.structure.dictionary.json meta.structure.dictionary.value.json meta.structure.dictionary.json meta.structure.dictionary.value.json meta.structure.dictionary.json meta.structure.dictionary.value.json meta.structure.dictionary.json meta.structure.dictionary.value.json meta.structure.dictionary.json meta.structure.dictionary.value.json meta.structure.dictionary.json meta.structure.dictionary.value.json meta.structure.dictionary.json meta.structure.dictionary.value.json meta.structure.dictionary.json meta.structure.dictionary.value.json meta.structure.dictionary.json support.type.property-name.json"],
      "settings": { "foreground": "#D4A520" }
    },
    {
      "name": "Markdown - Plain",
      "scope": ["text.html.markdown", "punctuation.definition.list_item.markdown"],
      "settings": { "foreground": "#666666" }
    },
    {
      "name": "Markdown - Raw Inline",
      "scope": ["text.html.markdown markup.inline.raw.markdown"],
      "settings": { "foreground": "#CE8C6A" }
    },
    {
      "name": "Markdown - Raw Inline Punctuation",
      "scope": ["text.html.markdown markup.inline.raw.markdown punctuation.definition.raw.markdown"],
      "settings": { "foreground": "#3A3A3A" }
    },
    {
      "name": "Markdown - Heading",
      "scope": [
        "markdown.heading",
        "markup.heading | markup.heading entity.name",
        "markup.heading.markdown punctuation.definition.heading.markdown",
        "punctuation.definition.heading.markdown"
      ],
      "settings": { "foreground": "#64B5F6", "fontStyle": "bold" }
    },
    {
      "name": "Markup - Italic",
      "scope": ["markup.italic"],
      "settings": { "fontStyle": "italic", "foreground": "#888888" }
    },
    {
      "name": "Markup - Bold",
      "scope": ["markup.bold", "markup.bold string"],
      "settings": { "fontStyle": "bold", "foreground": "#C0C0C0" }
    },
    {
      "name": "Markup - Bold-Italic",
      "scope": [
        "markup.bold markup.italic", "markup.italic markup.bold",
        "markup.quote markup.bold", "markup.bold markup.italic string",
        "markup.italic markup.bold string", "markup.quote markup.bold string"
      ],
      "settings": { "fontStyle": "bold italic", "foreground": "#C0C0C0" }
    },
    {
      "name": "Markup - Underline",
      "scope": ["markup.underline"],
      "settings": { "fontStyle": "underline", "foreground": "#888888" }
    },
    {
      "name": "Markdown - Blockquote",
      "scope": ["markup.quote punctuation.definition.blockquote.markdown"],
      "settings": { "foreground": "#3A3A3A" }
    },
    {
      "name": "Markup - Quote",
      "scope": ["markup.quote"],
      "settings": { "foreground": "#3A3A3A" }
    },
    {
      "name": "Markdown - Link",
      "scope": ["string.other.link.title.markdown"],
      "settings": { "foreground": "#64B5F6" }
    },
    {
      "name": "Markdown - Link Description",
      "scope": ["string.other.link.description.title.markdown"],
      "settings": { "foreground": "#E8A857" }
    },
    {
      "name": "Markdown - Link Anchor",
      "scope": ["constant.other.reference.link.markdown"],
      "settings": { "foreground": "#CE8C6A" }
    },
    {
      "name": "Markup - Raw Block",
      "scope": ["markup.raw.block"],
      "settings": { "foreground": "#CE8C6A" }
    },
    {
      "name": "Markdown - Raw Block Fenced",
      "scope": ["markup.raw.block.fenced.markdown"],
      "settings": { "foreground": "#666666" }
    },
    {
      "name": "Markdown - Fenced Code Block",
      "scope": ["punctuation.definition.fenced.markdown"],
      "settings": { "foreground": "#3A3A3A" }
    },
    {
      "name": "Markdown - Fenced Code Block Variable",
      "scope": [
        "markup.raw.block.fenced.markdown",
        "variable.language.fenced.markdown",
        "punctuation.section.class.end"
      ],
      "settings": { "foreground": "#666666" }
    },
    {
      "name": "Markdown - Fenced Language",
      "scope": ["variable.language.fenced.markdown"],
      "settings": { "foreground": "#E8A857" }
    },
    {
      "name": "Markdown - Separator",
      "scope": ["meta.separator"],
      "settings": { "fontStyle": "bold", "foreground": "#3A3A3A" }
    },
    {
      "name": "Markup - Table",
      "scope": ["markup.table"],
      "settings": { "foreground": "#666666" }
    }
  ]
}
